odoo/addons/project_subtask_parent_identification/README.rst
odoo/addons/project_subtask_parent_identification/__init__.py
odoo/addons/project_subtask_parent_identification/__manifest__.py
odoo/addons/project_subtask_parent_identification/models/__init__.py
odoo/addons/project_subtask_parent_identification/models/project_task.py
odoo/addons/project_subtask_parent_identification/readme/CONFIGURE.rst
odoo/addons/project_subtask_parent_identification/readme/CONTRIBUTORS.rst
odoo/addons/project_subtask_parent_identification/readme/DESCRIPTION.rst
odoo/addons/project_subtask_parent_identification/readme/USAGE.rst
odoo/addons/project_subtask_parent_identification/static/description/icon.png
odoo/addons/project_subtask_parent_identification/static/description/index.html
odoo/addons/project_subtask_parent_identification/tests/__init__.py
odoo/addons/project_subtask_parent_identification/tests/test_project_subtask_parent_identification.py
odoo/addons/project_subtask_parent_identification/views/project_task_views.xml
odoo_addon_project_subtask_parent_identification-16.0.1.0.0.1.dist-info/METADATA
odoo_addon_project_subtask_parent_identification-16.0.1.0.0.1.dist-info/WHEEL
odoo_addon_project_subtask_parent_identification-16.0.1.0.0.1.dist-info/top_level.txt
odoo_addon_project_subtask_parent_identification-16.0.1.0.0.1.dist-info/RECORD
